oar
ocraccuracyreporter
