Metadata-Version: 1.0
Name: ocraccuracyreporter
Version: 0.0.4
Summary: OCR Accuracy Reporter
Home-page: https://github.com/lucidprogrammer/ocraccuracyreporter
Author: Lucid Programmer
Author-email: lucidprogrammer@hotmail.com
License: MIT
Platform: UNKNOWN
